CyberTKAPI/__init__.py
CyberTKAPI/api.py
CyberTKAPI-2.9.2.dist-info/DESCRIPTION.rst
CyberTKAPI-2.9.2.dist-info/METADATA
CyberTKAPI-2.9.2.dist-info/RECORD
CyberTKAPI-2.9.2.dist-info/WHEEL
CyberTKAPI-2.9.2.dist-info/metadata.json
CyberTKAPI-2.9.2.dist-info/top_level.txt
