Metadata-Version: 2.0
Name: CyberTKAPI
Version: 2.9.2
Summary: CyberTK REST API v2
Home-page: https://github.com/CyberTKR/CyberTK-API
Author: CyberTK
Author-email: tolg@cybertkr.com
License: MIT
Platform: UNKNOWN
Classifier: Programming Language :: Python :: 3.6
Requires-Python: >=3.6.0
Requires-Dist: httpx (==0.19.0)
Requires-Dist: httpx[http2]
